webutils_wechat/__init__.py
webutils_wechat/common.py
webutils_wechat/auth/__init__.py
webutils_wechat/auth/flask/__init__.py
webutils_wechat/auth/flask/adaptor.py
webutils_wechat/auth/flask/resources.py
webutils_wechat/exceptions/__init__.py
webutils_wechat/exceptions/auth.py
webutils_wechat/exceptions/base.py
webutils_wechat/exceptions/utils.py
webutils_wechat/http_client/__init__.py
webutils_wechat/http_client/base.py
webutils_wechat/http_client/flask.py
webutils_wechat/logger/__init__.py
webutils_wechat/logger/config_data.py
webutils_wechat/redis/__init__.py
webutils_wechat/redis/client.py
webutils_wechat/redis/constants.py
webutils_wechat/redis/flask/__init__.py
webutils_wechat/wechat/__init__.py
webutils_wechat/wechat/adaptors/__init__.py
webutils_wechat/wechat/adaptors/access_token.py
webutils_wechat/wechat/adaptors/base.py
webutils_wechat/wechat/adaptors/qrcode.py
webutils_wechat/wechat/adaptors/user.py
webutils_wechat/wechat/flask/__init__.py
webutils_wechat/wechat/flask/adaptors/__init__.py
webutils_wechat/wechat/flask/adaptors/access_token.py
webutils_wechat-0.0.3.dist-info/METADATA
webutils_wechat-0.0.3.dist-info/WHEEL
webutils_wechat-0.0.3.dist-info/top_level.txt
webutils_wechat-0.0.3.dist-info/RECORD
